mujoco_scenes/__init__.py
mujoco_scenes/cli.py
mujoco_scenes/errors.py
mujoco_scenes/generate.py
mujoco_scenes/hfield.py
mujoco_scenes/mjcf.py
mujoco_scenes/py.typed
mujoco_scenes/templates/patch.xml
mujoco_scenes/templates/rough.xml
mujoco_scenes/templates/smooth.xml
mujoco_scenes/templates/smooth_hfield.xml
mujoco_scenes/templates/steps.xml
mujoco_scenes/templates/assets/patch_hfield.png
mujoco_scenes/templates/assets/rough_hfield.png
mujoco_scenes/templates/assets/steps_hfield.png
mujoco_scenes-0.0.16.dist-info/licenses/LICENSE
mujoco_scenes-0.0.16.dist-info/METADATA
mujoco_scenes-0.0.16.dist-info/WHEEL
mujoco_scenes-0.0.16.dist-info/entry_points.txt
mujoco_scenes-0.0.16.dist-info/top_level.txt
mujoco_scenes-0.0.16.dist-info/RECORD
