Metadata-Version: 2.4
Name: mujoco-scenes
Version: 0.0.16
Summary: The mujoco-scenes project
Home-page: https://github.com/kscalelabs/mujoco-scenes
Author: Benjamin Bolte
Requires-Python: >=3.11
License-File: LICENSE
Requires-Dist: etils
Requires-Dist: mujoco
Requires-Dist: numpy
Requires-Dist: Pillow
Provides-Extra: dev
Requires-Dist: black; extra == "dev"
Requires-Dist: darglint; extra == "dev"
Requires-Dist: mypy; extra == "dev"
Requires-Dist: pytest; extra == "dev"
Requires-Dist: ruff; extra == "dev"
Dynamic: author
Dynamic: description
Dynamic: description-content-type
Dynamic: home-page
Dynamic: license-file
Dynamic: provides-extra
Dynamic: requires-dist
Dynamic: requires-python
Dynamic: summary
